skej_llm/__init__.py
skej_llm/tools/__init__.py
skej_llm/tools/skej_llm_tool.py
skej_llm/tools/utils.py
skej_llm/yamls/skej_llm_tool.yaml
tests/__init__.py
tests/test_skej_llm_tool.py
skej_llm-0.0.13.dist-info/METADATA
skej_llm-0.0.13.dist-info/WHEEL
skej_llm-0.0.13.dist-info/entry_points.txt
skej_llm-0.0.13.dist-info/top_level.txt
skej_llm-0.0.13.dist-info/RECORD
