Metadata-Version: 2.1
Name: skej_llm
Version: 0.0.13
Summary: This is my tools package
